ibancheck/__init__.py
ibancheck/_ibancheck.py
ibancheck/_specs.py
ibancheck/registry_data.json
ibancheck-0.1.1.dist-info/LICENSE
ibancheck-0.1.1.dist-info/METADATA
ibancheck-0.1.1.dist-info/WHEEL
ibancheck-0.1.1.dist-info/top_level.txt
ibancheck-0.1.1.dist-info/RECORD
