Metadata-Version: 2.1
Name: ibancheck
Version: 0.1.1
Summary: Check if a IBAN bank account number is valid
Author-email: Thijs Janssen <thijs@thijsj.nl>
License: GNU GENERAL PUBLIC LICENSE
Project-URL: Homepage, https://github.com/thijsj/iban-check
Project-URL: Repository, https://github.com/thijsj/iban-check.git
Keywords: validate,IBAN
Classifier: Development Status :: 4 - Beta
Classifier: License :: OSI Approved :: GNU General Public License v3 (GPLv3)
Classifier: Programming Language :: Python :: 3
License-File: LICENSE
